sleap_nn/.DS_Store
sleap_nn/__init__.py
sleap_nn/cli.py
sleap_nn/evaluation.py
sleap_nn/legacy_models.py
sleap_nn/predict.py
sleap_nn/train.py
sleap_nn/architectures/__init__.py
sleap_nn/architectures/common.py
sleap_nn/architectures/convnext.py
sleap_nn/architectures/encoder_decoder.py
sleap_nn/architectures/heads.py
sleap_nn/architectures/model.py
sleap_nn/architectures/swint.py
sleap_nn/architectures/unet.py
sleap_nn/architectures/utils.py
sleap_nn/config/__init__.py
sleap_nn/config/data_config.py
sleap_nn/config/get_config.py
sleap_nn/config/model_config.py
sleap_nn/config/trainer_config.py
sleap_nn/config/training_job_config.py
sleap_nn/config/utils.py
sleap_nn/data/__init__.py
sleap_nn/data/augmentation.py
sleap_nn/data/confidence_maps.py
sleap_nn/data/custom_datasets.py
sleap_nn/data/edge_maps.py
sleap_nn/data/identity.py
sleap_nn/data/instance_centroids.py
sleap_nn/data/instance_cropping.py
sleap_nn/data/normalization.py
sleap_nn/data/providers.py
sleap_nn/data/resizing.py
sleap_nn/data/utils.py
sleap_nn/inference/__init__.py
sleap_nn/inference/bottomup.py
sleap_nn/inference/identity.py
sleap_nn/inference/paf_grouping.py
sleap_nn/inference/peak_finding.py
sleap_nn/inference/predictors.py
sleap_nn/inference/single_instance.py
sleap_nn/inference/topdown.py
sleap_nn/inference/utils.py
sleap_nn/tracking/__init__.py
sleap_nn/tracking/track_instance.py
sleap_nn/tracking/tracker.py
sleap_nn/tracking/utils.py
sleap_nn/tracking/candidates/__init__.py
sleap_nn/tracking/candidates/fixed_window.py
sleap_nn/tracking/candidates/local_queues.py
sleap_nn/training/__init__.py
sleap_nn/training/callbacks.py
sleap_nn/training/lightning_modules.py
sleap_nn/training/losses.py
sleap_nn/training/model_trainer.py
sleap_nn/training/utils.py
sleap_nn-0.0.3.dist-info/licenses/LICENSE
sleap_nn-0.0.3.dist-info/METADATA
sleap_nn-0.0.3.dist-info/WHEEL
sleap_nn-0.0.3.dist-info/entry_points.txt
sleap_nn-0.0.3.dist-info/top_level.txt
sleap_nn-0.0.3.dist-info/RECORD
