Metadata-Version: 2.4
Name: sleap-nn
Version: 0.0.3
Summary: Neural network backend for training and inference for animal pose estimation.
Author-email: Divya Seshadri Murali <dimurali@salk.edu>, Elizabeth Berrigan <eberrigan@salk.edu>, Vincent Tu <vitu@ucsd.edu>, Liezl Maree <lmaree@salk.edu>, David Samy <davidasamy@gmail.com>, Talmo Pereira <talmo@salk.edu>
License: BSD-3-Clause
Project-URL: Homepage, https://sleap.ai
Project-URL: Repository, https://github.com/talmolab/sleap-nn
Keywords: sleap,pose estimation,deep learning,neural networks,computer vision,animal behavior
Classifier: Programming Language :: Python :: 3.11
Classifier: Programming Language :: Python :: 3.12
Classifier: Programming Language :: Python :: 3.13
Requires-Python: <3.14,>=3.11
License-File: LICENSE
Requires-Dist: sleap-io>=0.2.0
Requires-Dist: numpy
Requires-Dist: lightning
Requires-Dist: kornia
Requires-Dist: jsonpickle
Requires-Dist: scipy
Requires-Dist: attrs
Requires-Dist: omegaconf
Requires-Dist: wandb
Requires-Dist: matplotlib
Requires-Dist: seaborn
Requires-Dist: rich
Requires-Dist: loguru
Requires-Dist: psutil
Requires-Dist: opencv-python
Requires-Dist: hydra-core
Requires-Dist: jupyter
Requires-Dist: jupyterlab
Requires-Dist: pyzmq
Provides-Extra: torch
Requires-Dist: torch; extra == "torch"
Requires-Dist: torchvision<0.24.0; extra == "torch"
Provides-Extra: torch-cpu
Requires-Dist: torch; extra == "torch-cpu"
Requires-Dist: torchvision<0.24.0; extra == "torch-cpu"
Provides-Extra: torch-cuda118
Requires-Dist: torch; extra == "torch-cuda118"
Requires-Dist: torchvision<0.24.0; extra == "torch-cuda118"
Provides-Extra: torch-cuda128
Requires-Dist: torch; extra == "torch-cuda128"
Requires-Dist: torchvision<0.24.0; extra == "torch-cuda128"
Provides-Extra: dev
Requires-Dist: pytest; extra == "dev"
Requires-Dist: pytest-cov; extra == "dev"
Requires-Dist: black; extra == "dev"
Requires-Dist: pydocstyle; extra == "dev"
Requires-Dist: toml; extra == "dev"
Requires-Dist: twine; extra == "dev"
Requires-Dist: build; extra == "dev"
Requires-Dist: ipython; extra == "dev"
Requires-Dist: ruff; extra == "dev"
Provides-Extra: docs
Requires-Dist: mkdocs; extra == "docs"
Requires-Dist: mkdocs-material; extra == "docs"
Requires-Dist: mkdocs-jupyter; extra == "docs"
Requires-Dist: mike; extra == "docs"
Requires-Dist: mkdocstrings[python]; extra == "docs"
Requires-Dist: mkdocs-gen-files; extra == "docs"
Requires-Dist: mkdocs-literate-nav; extra == "docs"
Requires-Dist: mkdocs-section-index; extra == "docs"
Dynamic: license-file
